typewriter/__init__.py
typewriter/typewriter.py
leza_typewriter-1.0.0.dist-info/METADATA
leza_typewriter-1.0.0.dist-info/WHEEL
leza_typewriter-1.0.0.dist-info/top_level.txt
leza_typewriter-1.0.0.dist-info/RECORD
