Metadata-Version: 2.1
Name: leza-typewriter
Version: 1.0.0
Summary: function for printing text in a type writer manner
Home-page: https://github.com/ElLoko233/typwriter
Author: Lelethu Futshane
License: UNKNOWN
Platform: UNKNOWN
Classifier: License :: OSI Approved :: MIT License
Classifier: Programming Language :: Python :: 3
Classifier: Programming Language :: Python :: 3.8
